PC_Adder.v
module PC_Adder(a,b,c);
    input [31:0] a,b;
    output [31:0] c;

    assign c = a + b;

endmodule

Instruction_Memory.v
module Instruction_Memory(rst,A,RD);

    input rst;
    input [31:0] A;

    output [31:0] RD;

    reg [31:0] mem [1023:0];

    assign RD = (rst == 1'b0) ? {32{1'b0}} : mem[A[31:2]];

    initial begin
        $readmemh("memfile.hex",mem,0,1023);
    end

    // initial begin
    //     mem[0] = 32'h0062E233;
    //     mem[1] = 32'h00B62423;
    // end
    
endmodule

PC.v
module PC_Module(clk,rst,PC,PC_Next);

    input clk,rst;
    input [31:0] PC_Next;

    output [31:0] PC;
    
    reg [31:0] PC;

    always @(posedge clk) begin
        if(rst == 1'b0)
            PC <= {32{1'b0}};
        else
            PC <= PC_Next;
    end

endmodule

Mux.v
module Mux(a,b,s,c);
    input [31:0] a,b;
    input s;

    output [31:0] c;

    assign c = (~s) ? a : b;

endmodule

Fetch_Cycle.v
`include "PC.v"
`include "Instruction_Memory.v"
`include "PC_Adder.v"
`include "Mux.v"

module fetch_cycle(clk,rst,PCSrcE,PCTargetE,InstrD,PCD,PCPlus4D);

    // Declaring input and output ports
    input clk,rst;
    input PCSrcE;
    input [31:0] PCTargetE;
    output [31:0] InstrD,PCD,PCPlus4D;

    // Declaring interim wires
    wire [31:0] PC_F,PCF,PCPlus4F;
    wire [31:0] InstrF;

    // Declaration of Register
    reg [31:0] InstrF_reg;
    reg [31:0] PCF_reg,PCPlus4F_reg;

    // Initiation of Modules
    // Declaring PC Mux

    Mux PC_MUX(
        .a(PCPlus4F),
        .b(PCTargetE),
        .s(PCSrcE),
        .c(PC_F)
    );

    // Declaring PC Counter
    PC_Module Program_Counter(
        .clk(clk),
        .rst(rst),
        .PC(PCF),
        .PC_Next(PC_F)
    );

    // Declaring Instruction Memory
    Instruction_Memory IMEM(
        .rst(rst),
        .A(PCF),
        .RD(InstrF)
    );

    // Declaring PC Adder
    PC_Adder PC_adder(
        .a(PCF),
        .b(32'h00000004),
        .c(PCPlus4F)
    );

    // Fetch Cycle Registers Logic
    always @(posedge clk or negedge rst) begin
        if(rst == 1'b0) begin
            InstrF_reg <= 32'h00000000;
            PCF_reg <= 32'h00000000;
            PCPlus4F_reg <= 32'h00000000;
        end
        else begin
            InstrF_reg <= InstrF;
            PCF_reg <= PCF;
            PCPlus4F_reg <= PCPlus4F;
        end
    end

    // Assign Registers Value to the Output Ports
    assign InstrD = (rst == 1'b0) ? 32'h00000000 : InstrF_reg;
    assign PCD = (rst == 1'b0) ? 32'h00000000 : PCF_reg;
    assign PCPlus4D = (rst == 1'b0) ? 32'h00000000 : PCPlus4F_reg;


endmodule

fetch_cycle_tb.v
module tb();

    // Declaring the inputs and outputs
    reg clk=0,rst,PCSrcE;
    reg [31:0] PCTargetE;
    wire [31:0] InstrD,PCD,PCPlus4D;
    
    // Declae the design under test
    fetch_cycle dut(
        .clk(clk),
        .rst(rst),
        .PCSrcE(PCSrcE),
        .PCTargetE(PCTargetE),
        .InstrD(InstrD),
        .PCD(PCD),
        .PCPlus4D(PCPlus4D)
    );

    // Generation of clock
    always begin
        clk = ~clk;
        #50;
    end

    // Provider the Stimulus
    initial begin
        rst <= 1'b0;
        #200;
        rst <= 1'b1;
        PCSrcE <= 1'b0;
        PCTargetE <= 32'h00000000;
        #500;
        $finish;
    end

    initial begin
        $dumpfile("dump.vcd");
        $dumpvars(0);
    end

endmodule

dump.vcd
$date
	Sun Jun  2 17:57:39 2024
$end
$version
	Icarus Verilog
$end
$timescale
	1s
$end
$scope module tb $end
$var wire 32 ! PCPlus4D [31:0] $end
$var wire 32 " PCD [31:0] $end
$var wire 32 # InstrD [31:0] $end
$var reg 1 $ PCSrcE $end
$var reg 32 % PCTargetE [31:0] $end
$var reg 1 & clk $end
$var reg 1 ' rst $end
$scope module dut $end
$var wire 1 $ PCSrcE $end
$var wire 32 ( PCTargetE [31:0] $end
$var wire 1 & clk $end
$var wire 1 ' rst $end
$var wire 32 ) PC_F [31:0] $end
$var wire 32 * PCPlus4F [31:0] $end
$var wire 32 + PCPlus4D [31:0] $end
$var wire 32 , PCF [31:0] $end
$var wire 32 - PCD [31:0] $end
$var wire 32 . InstrF [31:0] $end
$var wire 32 / InstrD [31:0] $end
$var reg 32 0 InstrF_reg [31:0] $end
$var reg 32 1 PCF_reg [31:0] $end
$var reg 32 2 PCPlus4F_reg [31:0] $end
$scope module IMEM $end
$var wire 1 ' rst $end
$var wire 32 3 RD [31:0] $end
$var wire 32 4 A [31:0] $end
$upscope $end
$scope module PC_MUX $end
$var wire 32 5 b [31:0] $end
$var wire 1 $ s $end
$var wire 32 6 c [31:0] $end
$var wire 32 7 a [31:0] $end
$upscope $end
$scope module PC_adder $end
$var wire 32 8 b [31:0] $end
$var wire 32 9 c [31:0] $end
$var wire 32 : a [31:0] $end
$upscope $end
$scope module Program_Counter $end
$var wire 32 ; PC_Next [31:0] $end
$var wire 1 & clk $end
$var wire 1 ' rst $end
$var reg 32 < PC [31:0] $end
$upscope $end
$upscope $end
$upscope $end
$enddefinitions $end
$comment Show the parameter values. $end
$dumpall
$end
#0
$dumpvars
bx <
bx ;
bx :
bx 9
b100 8
bx 7
bx 6
bx 5
bx 4
b0 3
b0 2
b0 1
b0 0
b0 /
b0 .
b0 -
bx ,
b0 +
bx *
bx )
bx (
0'
1&
bx %
x$
b0 #
b0 "
b0 !
$end
#50
0&
#100
b100 *
b100 7
b100 9
b0 ,
b0 4
b0 :
b0 <
1&
#150
0&
#200
b11000101110001110110011 .
b11000101110001110110011 3
b100 )
b100 6
b100 ;
b0 %
b0 (
b0 5
0$
1'
1&
#250
0&
#300
b11000101111010000110011 .
b11000101111010000110011 3
b1000 )
b1000 6
b1000 ;
b100 !
b100 +
b11000101110001110110011 #
b11000101110001110110011 /
b1000 *
b1000 7
b1000 9
b100 ,
b100 4
b100 :
b100 <
b100 2
b11000101110001110110011 0
1&
#350
0&
#400
bx .
bx 3
b1100 )
b1100 6
b1100 ;
b1000 !
b1000 +
b100 "
b100 -
b11000101111010000110011 #
b11000101111010000110011 /
b1100 *
b1100 7
b1100 9
b1000 ,
b1000 4
b1000 :
b1000 <
b1000 2
b100 1
b11000101111010000110011 0
1&
#450
0&
#500
b10000 )
b10000 6
b10000 ;
b1100 !
b1100 +
b1000 "
b1000 -
bx #
bx /
b10000 *
b10000 7
b10000 9
b1100 ,
b1100 4
b1100 :
b1100 <
b1100 2
b1000 1
bx 0
1&
#550
0&
#600
b10100 )
b10100 6
b10100 ;
b10000 !
b10000 +
b1100 "
b1100 -
b10100 *
b10100 7
b10100 9
b10000 ,
b10000 4
b10000 :
b10000 <
b10000 2
b1100 1
1&
#650
0&
#700
b11000 )
b11000 6
b11000 ;
b10100 !
b10100 +
b10000 "
b10000 -
b11000 *
b11000 7
b11000 9
b10100 ,
b10100 4
b10100 :
b10100 <
b10100 2
b10000 1
1&
